{
 "execution_paths": "315", 
 "callstack": false, 
 "reentrancy": false, 
 "modulo": false, 
 "division": false, 
 "execution_time": "18.9901709557", 
 "signedness": false, 
 "evm_code_coverage": "82.5", 
 "underflow": false, 
 "time_dependency": true, 
 "assertion_failure": false, 
 "timeout": false, 
 "dead_code": [
  "POP ", 
  "PUSH2 0x2037 ", 
  "MUL ", 
  "JUMP ", 
  "JUMPDEST ", 
  "PUSH2 0x200e ", 
  "PUSH1 0x04 ", 
  "PUSH1 0x20 ", 
  "DUP2 ", 
  "PUSH2 0x0e3f ", 
  "SHA3 ", 
  "JUMP ", 
  "JUMPDEST ", 
  "ISZERO ", 
  "PUSH2 0x201c ", 
  "ADD ", 
  "PUSH2 0x281b ", 
  "JUMPI ", 
  "PUSH1 0x00 ", 
  "SHA3 ", 
  "SWAP4 ", 
  "POP ", 
  "JUMPDEST ", 
  "GT ", 
  "JUMP ", 
  "JUMP ", 
  "JUMPDEST ", 
  "PUSH2 0x2025 ", 
  "POP ", 
  "PUSH1 0x00 ", 
  "DUP2 ", 
  "PUSH2 0x1867 ", 
  "PUSH2 0x285d ", 
  "JUMP ", 
  "JUMPDEST ", 
  "ISZERO ", 
  "PUSH2 0x2033 ", 
  "JUMPDEST ", 
  "DUP3 ", 
  "JUMPI ", 
  "PUSH1 0x00 ", 
  "PUSH2 0x2859 ", 
  "SWAP4 ", 
  "POP ", 
  "PUSH2 0x2037 ", 
  "PUSH1 0x00 ", 
  "JUMP ", 
  "JUMPDEST ", 
  "DUP1 ", 
  "SWAP4 ", 
  "POP ", 
  "ISZERO ", 
  "SSTORE ", 
  "PUSH1 0x01 ", 
  "DUP3 ", 
  "ADD ", 
  "PUSH1 0x00 ", 
  "SWAP1 ", 
  "SSTORE ", 
  "PUSH1 0x02 ", 
  "PUSH1 0x00 ", 
  "DUP3 ", 
  "ADD ", 
  "MSTORE ", 
  "DUP2 ", 
  "SSTORE ", 
  "PUSH1 0x03 ", 
  "DUP3 ", 
  "ADD ", 
  "PUSH1 0x00 ", 
  "SWAP2 ", 
  "SSTORE ", 
  "JUMPDEST ", 
  "PUSH1 0x08 ", 
  "POP ", 
  "SLOAD ", 
  "PUSH2 0x2258 ", 
  "SWAP1 ", 
  "SWAP2 ", 
  "SWAP1 ", 
  "PUSH4 0xffffffff ", 
  "JUMP ", 
  "JUMPDEST ", 
  "SWAP1 ", 
  "JUMP ", 
  "AND ", 
  "JUMP ", 
  "JUMPDEST ", 
  "SWAP1 ", 
  "POP ", 
  "SWAP1 ", 
  "JUMP ", 
  "MSTORE ", 
  "SWAP2 ", 
  "SWAP1 ", 
  "PUSH2 0x2821 ", 
  "DUP2 ", 
  "PUSH2 0x2037 ", 
  "MSTORE ", 
  "PUSH1 0x20 ", 
  "JUMPDEST ", 
  "JUMPDEST ", 
  "POP ", 
  "POP ", 
  "JUMP ", 
  "JUMPDEST ", 
  "JUMPI ", 
  "PUSH1 0x00 ", 
  "SWAP2 ", 
  "SWAP1 ", 
  "PUSH1 0x04 ", 
  "DUP1 ", 
  "PUSH1 0x20 ", 
  "GT ", 
  "SSTORE ", 
  "ISZERO ", 
  "ADD ", 
  "ADD ", 
  "JUMPI ", 
  "PUSH1 0x40 ", 
  "DUP1 ", 
  "SSTORE ", 
  "DUP3 ", 
  "JUMPDEST ", 
  "PUSH2 0x2258 ", 
  "ADD ", 
  "SWAP1 ", 
  "SWAP2 ", 
  "SWAP1 ", 
  "PUSH4 0xffffffff ", 
  "PUSH1 0x00 ", 
  "AND ", 
  "JUMP ", 
  "JUMPDEST ", 
  "GT ", 
  "SWAP1 ", 
  "POP ", 
  "SWAP2 ", 
  "SWAP1 ", 
  "POP ", 
  "JUMP ", 
  "DUP1 ", 
  "PUSH1 0x00 ", 
  "PUSH1 0x00 ", 
  "DUP2 ", 
  "SWAP1 ", 
  "GT ", 
  "DUP2 ", 
  "DUP4 ", 
  "JUMPDEST ", 
  "PUSH1 0x40 ", 
  "MLOAD ", 
  "DUP1 ", 
  "DUP3 ", 
  "DUP2 ", 
  "MSTORE ", 
  "PUSH1 0x20 ", 
  "ADD ", 
  "SWAP2 ", 
  "POP ", 
  "POP ", 
  "PUSH1 0x40 ", 
  "MLOAD ", 
  "DUP1 ", 
  "SWAP2 ", 
  "SUB ", 
  "SWAP1 ", 
  "RETURN ", 
  "SWAP1 ", 
  "POP ", 
  "PUSH1 0x04 ", 
  "DUP1 ", 
  "ADD ", 
  "PUSH2 0x2827 ", 
  "JUMPDEST ", 
  "STOP ", 
  "SWAP1 ", 
  "JUMP ", 
  "JUMPDEST ", 
  "MSTORE ", 
  "POP ", 
  "SWAP1 ", 
  "STOP ", 
  "DUP2 ", 
  "DUP3 ", 
  "MSTORE ", 
  "PUSH1 0x20 ", 
  "JUMPDEST ", 
  "PUSH1 0x40 ", 
  "MLOAD ", 
  "DUP1 ", 
  "DUP3 ", 
  "PUSH20 0xffffffffffffffffffffffffffffffffffffffff ", 
  "ADD ", 
  "SSTORE ", 
  "PUSH1 0x20 ", 
  "AND ", 
  "PUSH20 0xffffffffffffffffffffffffffffffffffffffff ", 
  "SWAP2 ", 
  "AND ", 
  "DUP2 ", 
  "MSTORE ", 
  "PUSH1 0x20 ", 
  "ADD ", 
  "SWAP2 ", 
  "POP ", 
  "POP ", 
  "PUSH1 0x40 ", 
  "MLOAD ", 
  "DUP1 ", 
  "SWAP2 ", 
  "SUB ", 
  "SWAP1 ", 
  "RETURN ", 
  "JUMPDEST ", 
  "GT ", 
  "JUMP ", 
  "DUP9 ", 
  "SWAP2 ", 
  "SWAP3 ", 
  "MLOAD ", 
  "PUSH1 0x20 ", 
  "PUSH1 0x20 ", 
  "PUSH1 0x01 ", 
  "DUP3 ", 
  "DUP1 ", 
  "ADD ", 
  "DUP3 ", 
  "PUSH2 0x2618 ", 
  "JUMPDEST ", 
  "JUMPDEST ", 
  "POP ", 
  "POP ", 
  "POP ", 
  "JUMP ", 
  "SWAP2 ", 
  "JUMPDEST ", 
  "DUP1 ", 
  "DUP3 ", 
  "GT ", 
  "ISZERO ", 
  "PUSH2 0x248b ", 
  "PUSH2 0x27ef ", 
  "JUMPI ", 
  "PUSH1 0x00 ", 
  "DUP2 ", 
  "PUSH1 0x00 ", 
  "SWAP1 ", 
  "SSTORE ", 
  "POP ", 
  "PUSH1 0x01 ", 
  "ADD ", 
  "PUSH2 0x2473 ", 
  "JUMP ", 
  "JUMPDEST ", 
  "POP ", 
  "SWAP1 ", 
  "JUMP ", 
  "JUMPDEST ", 
  "SWAP1 ", 
  "JUMP ", 
  "JUMPDEST ", 
  "PUSH1 0x00 ", 
  "DUP1 ", 
  "PUSH1 0x00 ", 
  "SWAP2 ", 
  "DUP1 ", 
  "PUSH1 0x00 ", 
  "DUP1 ", 
  "DUP11 ", 
  "PUSH1 0x05 ", 
  "DUP2 ", 
  "SWAP1 ", 
  "SSTORE ", 
  "POP ", 
  "DUP10 ", 
  "PUSH1 0x00 ", 
  "DUP2 ", 
  "SWAP1 ", 
  "SSTORE ", 
  "POP ", 
  "DUP9 ", 
  "PUSH1 0x01 ", 
  "DUP2 ", 
  "SWAP1 ", 
  "SSTORE ", 
  "POP ", 
  "DUP8 ", 
  "PUSH1 0x02 ", 
  "DUP2 ", 
  "SWAP1 ", 
  "SSTORE ", 
  "POP ", 
  "DUP7 ", 
  "PUSH1 0x03 ", 
  "DUP2 ", 
  "SWAP1 ", 
  "SSTORE ", 
  "POP ", 
  "PUSH1 0x0a ", 
  "PUSH1 0x05 ", 
  "SLOAD ", 
  "MUL ", 
  "PUSH9 0x015af1d78b58c40000 ", 
  "SHA3 ", 
  "DUP2 ", 
  "ISZERO ", 
  "ISZERO ", 
  "PUSH2 0x24d7 ", 
  "JUMPI ", 
  "ASSERTFAIL ", 
  "JUMPDEST ", 
  "DIV ", 
  "SWAP6 ", 
  "POP ", 
  "PUSH1 0x04 ", 
  "DUP1 ", 
  "SLOAD ", 
  "DUP1 ", 
  "PUSH1 0x01 ", 
  "ADD ", 
  "DUP3 ", 
  "DUP2 ", 
  "PUSH2 0x24ee ", 
  "SWAP2 ", 
  "SWAP1 ", 
  "PUSH2 0x27ef ", 
  "JUMPDEST ", 
  "SWAP2 ", 
  "PUSH1 0x00 ", 
  "JUMPDEST ", 
  "MSTORE ", 
  "PUSH1 0x20 ", 
  "PUSH1 0x00 ", 
  "PUSH1 0x20 ", 
  "SHA3 ", 
  "SWAP1 ", 
  "ADD ", 
  "SHA3 ", 
  "SWAP1 ", 
  "DUP6 ", 
  "SWAP1 ", 
  "MUL ", 
  "ADD ", 
  "SWAP2 ", 
  "PUSH2 0x0100 ", 
  "PUSH1 0x80 ", 
  "EXP ", 
  "DUP2 ", 
  "SLOAD ", 
  "DUP2 ", 
  "PUSH20 0xffffffffffffffffffffffffffffffffffffffff ", 
  "ADD ", 
  "PUSH1 0x40 ", 
  "MSTORE ", 
  "DUP1 ", 
  "TIMESTAMP ", 
  "DUP2 ", 
  "MSTORE ", 
  "PUSH1 0x20 ", 
  "ADD ", 
  "PUSH1 0x00 ", 
  "PUSH1 0x0f ", 
  "SLOAD ", 
  "DUP2 ", 
  "MSTORE ", 
  "PUSH1 0x20 ", 
  "ADD ", 
  "PUSH1 0x00 ", 
  "MUL ", 
  "DUP2 ", 
  "AND ", 
  "PUSH1 0x20 ", 
  "DUP4 ", 
  "ADD ", 
  "DUP11 ", 
  "DUP2 ", 
  "MSTORE ", 
  "POP ", 
  "SWAP1 ", 
  "SWAP2 ", 
  "SWAP1 ", 
  "SWAP2 ", 
  "POP ", 
  "PUSH1 0x00 ", 
  "DUP3 ", 
  "ADD ", 
  "MLOAD ", 
  "DUP2 ", 
  "PUSH1 0x00 ", 
  "ADD ", 
  "SSTORE ", 
  "PUSH1 0x20 ", 
  "AND ", 
  "MUL ", 
  "OR ", 
  "SWAP1 ", 
  "SSTORE ", 
  "POP ", 
  "POP ", 
  "ADD ", 
  "SSTORE ", 
  "PUSH1 0x40 ", 
  "DUP3 ", 
  "ADD ", 
  "MLOAD ", 
  "DUP2 ", 
  "PUSH1 0x02 ", 
  "ADD ", 
  "SSTORE ", 
  "PUSH1 0x60 ", 
  "JUMPDEST ", 
  "DUP3 ", 
  "ADD ", 
  "MLOAD ", 
  "DUP2 ", 
  "PUSH1 0x03 ", 
  "ADD ", 
  "SSTORE ", 
  "POP ", 
  "POP ", 
  "POP ", 
  "PUSH2 0x255d ", 
  "PUSH1 0x05 ", 
  "PUSH2 0x1045 ", 
  "JUMP ", 
  "JUMPDEST ", 
  "SWAP5 ", 
  "POP ", 
  "PUSH1 0x04 ", 
  "DUP1 ", 
  "SLOAD ", 
  "DUP1 ", 
  "PUSH1 0x01 ", 
  "ADD ", 
  "DUP3 ", 
  "DUP2 ", 
  "PUSH2 0x2573 ", 
  "SWAP2 ", 
  "SWAP1 ", 
  "PUSH2 0x27ef ", 
  "JUMP ", 
  "JUMPDEST ", 
  "SWAP2 ", 
  "PUSH1 0x00 ", 
  "MSTORE ", 
  "PUSH1 0x20 ", 
  "PUSH1 0x00 ", 
  "SHA3 ", 
  "SWAP1 ", 
  "PUSH1 0x04 ", 
  "MUL ", 
  "ADD ", 
  "PUSH1 0x00 ", 
  "PUSH1 0x80 ", 
  "PUSH1 0x40 ", 
  "MLOAD ", 
  "SWAP1 ", 
  "DUP2 ", 
  "ADD ", 
  "PUSH1 0x40 ", 
  "MSTORE ", 
  "JUMP ", 
  "PUSH1 0x00 ", 
  "SLOAD ", 
  "DUP2 ", 
  "MSTORE ", 
  "PUSH1 0x20 ", 
  "ADD ", 
  "PUSH1 0x01 ", 
  "SLOAD ", 
  "SWAP2 ", 
  "MSTORE ", 
  "PUSH1 0x20 ", 
  "ADD ", 
  "PUSH1 0x14 ", 
  "PUSH1 0x00 ", 
  "DUP2 ", 
  "MSTORE ", 
  "PUSH1 0x20 ", 
  "MSTORE ", 
  "ADD ", 
  "DUP10 ", 
  "DUP2 ", 
  "MSTORE ", 
  "POP ", 
  "SWAP1 ", 
  "SWAP2 ", 
  "MSTORE ", 
  "SWAP2 ", 
  "POP ", 
  "PUSH1 0x00 ", 
  "DUP3 ", 
  "ADD ", 
  "MLOAD ", 
  "DUP2 ", 
  "PUSH1 0x00 ", 
  "ADD ", 
  "ADD ", 
  "SSTORE ", 
  "PUSH1 0x20 ", 
  "DUP3 ", 
  "ADD ", 
  "MLOAD ", 
  "PUSH1 0x00 ", 
  "PUSH1 0x01 ", 
  "POP ", 
  "ADD ", 
  "SSTORE ", 
  "PUSH1 0x40 ", 
  "DUP3 ", 
  "ADD ", 
  "MLOAD ", 
  "DUP2 ", 
  "PUSH1 0x02 ", 
  "PUSH1 0x00 ", 
  "ADD ", 
  "SSTORE ", 
  "PUSH1 0x60 ", 
  "POP ", 
  "DUP3 ", 
  "ADD ", 
  "MLOAD ", 
  "DUP2 ", 
  "PUSH1 0x03 ", 
  "SWAP1 ", 
  "ADD ", 
  "PUSH1 0x04 ", 
  "POP ", 
  "POP ", 
  "POP ", 
  "PUSH2 0x25e4 ", 
  "PUSH1 0x0a ", 
  "PUSH2 0x1045 ", 
  "SWAP2 ", 
  "JUMPDEST ", 
  "SWAP4 ", 
  "POP ", 
  "PUSH3 0x093a80 ", 
  "SWAP1 ", 
  "PUSH1 0x02 ", 
  "SLOAD ", 
  "ADD ", 
  "PUSH1 0x00 ", 
  "POP ", 
  "PUSH3 0x1baf80 ", 
  "PUSH1 0x00 ", 
  "PUSH1 0x02 ", 
  "SLOAD ", 
  "ADD ", 
  "SWAP2 ", 
  "POP ", 
  "PUSH3 0x127500 ", 
  "PUSH1 0x02 ", 
  "SLOAD ", 
  "ADD ", 
  "SWAP1 ", 
  "POP ", 
  "PUSH1 0x04 ", 
  "PUSH1 0x40 ", 
  "SLOAD ", 
  "DUP1 ", 
  "PUSH1 0x01 ", 
  "MLOAD ", 
  "JUMPDEST ", 
  "PUSH1 0x40 ", 
  "DUP2 ", 
  "MLOAD ", 
  "DUP1 ", 
  "DUP3 ", 
  "DUP2 ", 
  "MSTORE ", 
  "PUSH1 0x20 ", 
  "ADD ", 
  "SWAP2 ", 
  "POP ", 
  "POP ", 
  "PUSH1 0x40 ", 
  "MLOAD ", 
  "DUP1 ", 
  "SWAP2 ", 
  "SUB ", 
  "SWAP1 ", 
  "RETURN ", 
  "SWAP1 ", 
  "PUSH1 0x04 ", 
  "MUL ", 
  "ADD ", 
  "PUSH1 0x00 ", 
  "PUSH1 0x80 ", 
  "PUSH1 0x40 ", 
  "MLOAD ", 
  "SWAP1 ", 
  "DUP2 ", 
  "ADD ", 
  "PUSH1 0x40 ", 
  "MSTORE ", 
  "DUP1 ", 
  "PUSH1 0x02 ", 
  "SLOAD ", 
  "DUP2 ", 
  "MSTORE ", 
  "PUSH1 0x20 ", 
  "ADD ", 
  "DUP8 ", 
  "DUP2 ", 
  "MSTORE ", 
  "PUSH1 0x20 ", 
  "ADD ", 
  "JUMPDEST ", 
  "PUSH1 0x40 ", 
  "DUP2 ", 
  "MLOAD ", 
  "DUP1 ", 
  "DUP3 ", 
  "ISZERO ", 
  "ISZERO ", 
  "ISZERO ", 
  "ISZERO ", 
  "DUP2 ", 
  "MSTORE ", 
  "PUSH1 0x20 ", 
  "SWAP1 ", 
  "ADD ", 
  "SWAP2 ", 
  "POP ", 
  "POP ", 
  "PUSH1 0x40 ", 
  "ADD ", 
  "MLOAD ", 
  "DUP1 ", 
  "SWAP2 ", 
  "SUB ", 
  "SWAP1 ", 
  "RETURN ", 
  "PUSH1 0x20 ", 
  "DUP3 ", 
  "ADD ", 
  "MLOAD ", 
  "DUP2 ", 
  "PUSH1 0x01 ", 
  "DUP2 ", 
  "SSTORE ", 
  "PUSH1 0x40 ", 
  "DUP2 ", 
  "DUP3 ", 
  "ADD ", 
  "MLOAD ", 
  "DUP2 ", 
  "PUSH1 0x02 ", 
  "ADD ", 
  "SSTORE ", 
  "PUSH1 0x60 ", 
  "DUP3 ", 
  "ADD ", 
  "MLOAD ", 
  "DUP2 ", 
  "PUSH1 0x03 ", 
  "ADD ", 
  "SWAP2 ", 
  "POP ", 
  "POP ", 
  "POP ", 
  "PUSH1 0x04 ", 
  "DUP1 ", 
  "SLOAD ", 
  "DUP1 ", 
  "PUSH1 0x01 ", 
  "ADD ", 
  "DUP3 ", 
  "DUP2 ", 
  "PUSH2 0x2691 ", 
  "SWAP2 ", 
  "SWAP1 ", 
  "PUSH2 0x27ef ", 
  "JUMP ", 
  "JUMPDEST ", 
  "SWAP2 ", 
  "PUSH1 0x00 ", 
  "MSTORE ", 
  "PUSH1 0x20 ", 
  "PUSH1 0x00 ", 
  "DUP3 ", 
  "SHA3 ", 
  "SWAP1 ", 
  "PUSH1 0x04 ", 
  "MUL ", 
  "ADD ", 
  "PUSH1 0x00 ", 
  "PUSH1 0x80 ", 
  "NOT ", 
  "PUSH1 0x40 ", 
  "MLOAD ", 
  "SWAP1 ", 
  "DUP2 ", 
  "MSTORE ", 
  "MSTORE ", 
  "MSTORE ", 
  "DUP1 ", 
  "DUP8 ", 
  "SWAP1 ", 
  "MSTORE ", 
  "PUSH1 0x20 ", 
  "ADD ", 
  "DUP6 ", 
  "DUP2 ", 
  "SWAP2 ", 
  "PUSH1 0x20 ", 
  "ADD ", 
  "PUSH1 0x0a ", 
  "PUSH20 0xffffffffffffffffffffffffffffffffffffffff ", 
  "DUP2 ", 
  "MSTORE ", 
  "PUSH1 0x20 ", 
  "ADD ", 
  "DUP9 ", 
  "JUMPDEST ", 
  "STOP ", 
  "POP ", 
  "SWAP1 ", 
  "SWAP2 ", 
  "SWAP1 ", 
  "SWAP2 ", 
  "POP ", 
  "PUSH1 0x00 ", 
  "DUP3 ", 
  "ADD ", 
  "MLOAD ", 
  "DUP2 ", 
  "PUSH1 0x00 ", 
  "ADD ", 
  "SSTORE ", 
  "POP ", 
  "DUP3 ", 
  "ADD ", 
  "MLOAD ", 
  "DUP2 ", 
  "PUSH1 0x01 ", 
  "ADD ", 
  "SSTORE ", 
  "PUSH1 0x40 ", 
  "DUP3 ", 
  "ADD ", 
  "MLOAD ", 
  "DUP2 ", 
  "PUSH1 0x02 ", 
  "ADD ", 
  "SSTORE ", 
  "PUSH1 0x60 ", 
  "DUP3 ", 
  "ADD ", 
  "MLOAD ", 
  "DUP2 ", 
  "PUSH1 0x03 ", 
  "ADD ", 
  "SSTORE ", 
  "POP ", 
  "POP ", 
  "POP ", 
  "PUSH1 0x04 ", 
  "DUP1 ", 
  "SLOAD ", 
  "DUP1 ", 
  "PUSH1 0x01 ", 
  "ADD ", 
  "DUP3 ", 
  "DUP2 ", 
  "PUSH2 0x2708 ", 
  "SWAP2 ", 
  "SWAP1 ", 
  "PUSH2 0x27ef ", 
  "JUMP ", 
  "JUMPDEST ", 
  "SWAP2 ", 
  "PUSH1 0x00 ", 
  "MSTORE ", 
  "PUSH1 0x20 ", 
  "PUSH1 0x00 ", 
  "SHA3 ", 
  "SWAP1 ", 
  "PUSH1 0x04 ", 
  "MUL ", 
  "ADD ", 
  "PUSH1 0x00 ", 
  "PUSH1 0x80 ", 
  "PUSH1 0x40 ", 
  "MLOAD ", 
  "SWAP1 ", 
  "DUP2 ", 
  "ADD ", 
  "PUSH1 0x40 ", 
  "MSTORE ", 
  "DUP1 ", 
  "DUP6 ", 
  "DUP2 ", 
  "JUMPDEST ", 
  "GT ", 
  "ADD ", 
  "DUP7 ", 
  "DUP2 ", 
  "MSTORE ", 
  "DUP3 ", 
  "ADD ", 
  "PUSH1 0x05 ", 
  "DUP2 ", 
  "MSTORE ", 
  "PUSH1 0x20 ", 
  "ADD ", 
  "DUP9 ", 
  "DUP2 ", 
  "MSTORE ", 
  "POP ", 
  "SWAP1 ", 
  "SWAP2 ", 
  "SWAP1 ", 
  "DUP3 ", 
  "POP ", 
  "PUSH1 0x00 ", 
  "DUP3 ", 
  "ADD ", 
  "ADD ", 
  "DUP2 ", 
  "PUSH1 0x00 ", 
  "ADD ", 
  "SSTORE ", 
  "MLOAD ", 
  "DUP3 ", 
  "ADD ", 
  "MLOAD ", 
  "DUP2 ", 
  "DUP2 ", 
  "ADD ", 
  "SSTORE ", 
  "PUSH1 0x40 ", 
  "PUSH1 0x01 ", 
  "ADD ", 
  "MLOAD ", 
  "DUP2 ", 
  "PUSH1 0x02 ", 
  "ADD ", 
  "SSTORE ", 
  "PUSH1 0x60 ", 
  "DUP3 ", 
  "ADD ", 
  "MLOAD ", 
  "DUP2 ", 
  "PUSH1 0x03 ", 
  "ADD ", 
  "SSTORE ", 
  "PUSH1 0x00 ", 
  "POP ", 
  "POP ", 
  "PUSH1 0x04 ", 
  "DUP1 ", 
  "SLOAD ", 
  "SWAP1 ", 
  "PUSH1 0x01 ", 
  "ADD ", 
  "DUP3 ", 
  "DUP2 ", 
  "PUSH2 0x277f ", 
  "SWAP2 ", 
  "SWAP1 ", 
  "PUSH2 0x27ef ", 
  "JUMP ", 
  "JUMPDEST ", 
  "SWAP2 ", 
  "PUSH1 0x00 ", 
  "MSTORE ", 
  "PUSH1 0x20 ", 
  "PUSH1 0x00 ", 
  "MLOAD ", 
  "SWAP1 ", 
  "PUSH1 0x04 ", 
  "MUL ", 
  "ADD ", 
  "PUSH1 0x00 ", 
  "POP ", 
  "PUSH1 0x80 ", 
  "PUSH1 0x40 ", 
  "MLOAD ", 
  "SWAP1 ", 
  "DUP2 ", 
  "ADD ", 
  "PUSH1 0x40 ", 
  "MSTORE ", 
  "DUP1 ", 
  "DUP7 ", 
  "DUP2 ", 
  "MSTORE ", 
  "PUSH1 0x20 ", 
  "ADD ", 
  "DUP12 ", 
  "DUP2 ", 
  "MSTORE ", 
  "PUSH1 0x20 ", 
  "SWAP1 ", 
  "ADD ", 
  "PUSH1 0x00 ", 
  "DUP2 ", 
  "MSTORE ", 
  "PUSH1 0x20 ", 
  "ADD ", 
  "DUP9 ", 
  "DUP2 ", 
  "MSTORE ", 
  "POP ", 
  "SWAP1 ", 
  "SWAP2 ", 
  "SWAP1 ", 
  "SWAP2 ", 
  "POP ", 
  "PUSH1 0x00 ", 
  "SWAP1 ", 
  "DUP3 ", 
  "ADD ", 
  "MLOAD ", 
  "DUP2 ", 
  "PUSH1 0x00 ", 
  "ADD ", 
  "SSTORE ", 
  "PUSH1 0x20 ", 
  "DUP2 ", 
  "ADD ", 
  "MLOAD ", 
  "DUP2 ", 
  "PUSH1 0x01 ", 
  "ADD ", 
  "SSTORE ", 
  "PUSH1 0x40 ", 
  "DUP3 ", 
  "ADD ", 
  "MLOAD ", 
  "DUP2 ", 
  "PUSH1 0x02 ", 
  "ADD ", 
  "SSTORE ", 
  "PUSH1 0x60 ", 
  "PUSH2 0x281c ", 
  "DUP3 ", 
  "ADD ", 
  "MLOAD ", 
  "DUP2 ", 
  "PUSH1 0x03 ", 
  "ADD ", 
  "SSTORE ", 
  "POP ", 
  "POP ", 
  "ADD ", 
  "POP ", 
  "POP ", 
  "POP ", 
  "POP ", 
  "POP ", 
  "JUMP ", 
  "POP ", 
  "POP ", 
  "POP ", 
  "POP ", 
  "POP ", 
  "JUMP ", 
  "JUMPDEST ", 
  "DUP2 ", 
  "SLOAD ", 
  "DUP2 ", 
  "DUP4 ", 
  "SSTORE ", 
  "DUP2 ", 
  "DUP2 ", 
  "JUMPDEST ", 
  "ISZERO ", 
  "PUSH2 0x2005 ", 
  "MUL ", 
  "JUMPI ", 
  "PUSH1 0x00 ", 
  "SWAP4 "
 ], 
 "overflow": false, 
 "money_concurrency": true, 
 "truncation": false
}