{
 "execution_paths": "82", 
 "callstack": false, 
 "reentrancy": false, 
 "modulo": false, 
 "division": false, 
 "execution_time": "14.879830122", 
 "signedness": false, 
 "evm_code_coverage": "96.2", 
 "underflow": false, 
 "time_dependency": false, 
 "assertion_failure": false, 
 "timeout": false, 
 "dead_code": [
  "STOP ", 
  "JUMPDEST ", 
  "PUSH1 0x40 ", 
  "MLOAD ", 
  "SWAP1 ", 
  "ISZERO ", 
  "ISZERO ", 
  "DUP2 ", 
  "MSTORE ", 
  "PUSH1 0x20 ", 
  "ADD ", 
  "PUSH1 0x40 ", 
  "MLOAD ", 
  "DUP1 ", 
  "SWAP2 ", 
  "SUB ", 
  "SWAP1 ", 
  "RETURN ", 
  "JUMPDEST ", 
  "POP ", 
  "PUSH1 0x00 ", 
  "SWAP2 ", 
  "DUP3 ", 
  "MSTORE ", 
  "PUSH1 0x20 ", 
  "SWAP1 ", 
  "SWAP2 ", 
  "SHA3 ", 
  "ADD ", 
  "DUP2 ", 
  "SWAP1 ", 
  "SSTORE "
 ], 
 "overflow": false, 
 "money_concurrency": false, 
 "truncation": false
}