{
 "execution_paths": "55", 
 "callstack": false, 
 "reentrancy": false, 
 "modulo": false, 
 "division": false, 
 "execution_time": "42.7146449089", 
 "signedness": false, 
 "evm_code_coverage": "81.5", 
 "underflow": false, 
 "time_dependency": false, 
 "assertion_failure": false, 
 "timeout": false, 
 "dead_code": [
  "LOG1 ", 
  "RETURN ", 
  "PUSH1 0x00 ", 
  "AND ", 
  "PUSH20 0xffffffffffffffffffffffffffffffffffffffff ", 
  "DUP1 ", 
  "AND ", 
  "PUSH4 0xa9059cbb ", 
  "CALLER ", 
  "DUP4 ", 
  "PUSH1 0x00 ", 
  "PUSH1 0x40 ", 
  "MLOAD ", 
  "PUSH1 0x20 ", 
  "ADD ", 
  "MSTORE ", 
  "PUSH1 0x40 ", 
  "MLOAD ", 
  "DUP4 ", 
  "PUSH4 0xffffffff ", 
  "AND ", 
  "PUSH29 0x0100000000000000000000000000000000000000000000000000000000 ", 
  "STOP ", 
  "PUSH1 0x40 ", 
  "MUL ", 
  "DUP2 ", 
  "MSTORE ", 
  "PUSH1 0x04 ", 
  "ADD ", 
  "DUP1 ", 
  "DUP4 ", 
  "PUSH20 0xffffffffffffffffffffffffffffffffffffffff ", 
  "DUP3 ", 
  "DUP2 ", 
  "MSTORE ", 
  "DUP1 ", 
  "AND ", 
  "PUSH20 0xffffffffffffffffffffffffffffffffffffffff ", 
  "PUSH1 0x20 ", 
  "SWAP2 ", 
  "AND ", 
  "DUP2 ", 
  "MSTORE ", 
  "PUSH1 0x20 ", 
  "PUSH1 0x00 ", 
  "ADD ", 
  "DUP3 ", 
  "DUP2 ", 
  "MSTORE ", 
  "PUSH1 0x20 ", 
  "SWAP2 ", 
  "ADD ", 
  "SWAP3 ", 
  "POP ", 
  "POP ", 
  "POP ", 
  "PUSH1 0x20 ", 
  "PUSH1 0x40 ", 
  "MLOAD ", 
  "DUP1 ", 
  "DUP4 ", 
  "SUB ", 
  "DUP2 ", 
  "PUSH1 0x00 ", 
  "DUP8 ", 
  "DUP1 ", 
  "EXTCODESIZE ", 
  "ISZERO ", 
  "ISZERO ", 
  "PUSH2 0x02b4 ", 
  "DUP1 ", 
  "JUMPI ", 
  "PUSH1 0x00 ", 
  "DUP1 ", 
  "REVERT ", 
  "JUMPDEST ", 
  "PUSH2 0x02c6 ", 
  "GAS ", 
  "SUB ", 
  "CALL ", 
  "ISZERO ", 
  "ISZERO ", 
  "PUSH2 0x02c5 ", 
  "SWAP1 ", 
  "JUMPI ", 
  "PUSH1 0x00 ", 
  "DUP1 ", 
  "REVERT ", 
  "JUMPDEST ", 
  "POP ", 
  "POP ", 
  "POP ", 
  "PUSH1 0x40 ", 
  "MLOAD ", 
  "DUP1 ", 
  "MLOAD ", 
  "SWAP1 ", 
  "POP ", 
  "POP ", 
  "PUSH32 0x1d72140a7ccdb496bef50918d2598dd7edefb514f70e6d4beb528cbd16c80b7d ", 
  "PUSH1 0x00 ", 
  "DUP1 ", 
  "REVERT ", 
  "JUMPDEST ", 
  "DUP1 ", 
  "SWAP2 ", 
  "POP ", 
  "POP ", 
  "POP ", 
  "SWAP2 ", 
  "POP ", 
  "POP ", 
  "JUMP ", 
  "CALLER ", 
  "DUP3 ", 
  "PUSH1 0x40 ", 
  "MLOAD ", 
  "DUP1 ", 
  "DUP4 ", 
  "PUSH20 0xffffffffffffffffffffffffffffffffffffffff ", 
  "POP ", 
  "JUMPDEST ", 
  "SWAP1 ", 
  "POP ", 
  "PUSH1 0x02 ", 
  "PUSH1 0x00 ", 
  "SWAP1 ", 
  "SLOAD ", 
  "SWAP1 ", 
  "PUSH2 0x0100 ", 
  "SWAP3 ", 
  "EXP ", 
  "SWAP1 ", 
  "DIV ", 
  "PUSH20 0xffffffffffffffffffffffffffffffffffffffff ", 
  "AND ", 
  "PUSH20 0xffffffffffffffffffffffffffffffffffffffff ", 
  "JUMPDEST ", 
  "MLOAD ", 
  "STOP ", 
  "AND ", 
  "PUSH20 0xffffffffffffffffffffffffffffffffffffffff ", 
  "AND ", 
  "DUP2 ", 
  "MSTORE ", 
  "PUSH1 0x20 ", 
  "ADD ", 
  "DUP3 ", 
  "DUP2 ", 
  "MSTORE ", 
  "PUSH1 0x20 ", 
  "ADD ", 
  "SWAP3 ", 
  "POP ", 
  "POP ", 
  "POP ", 
  "PUSH1 0x40 ", 
  "MLOAD ", 
  "DUP1 ", 
  "AND ", 
  "PUSH4 0x70a08231 ", 
  "SWAP1 ", 
  "LOG1 ", 
  "PUSH2 0x03b0 ", 
  "POP ", 
  "ADDRESS ", 
  "PUSH1 0x00 ", 
  "JUMPDEST ", 
  "PUSH1 0x40 ", 
  "MLOAD ", 
  "PUSH1 0x20 ", 
  "ADD ", 
  "MSTORE ", 
  "PUSH1 0x40 ", 
  "MLOAD ", 
  "DUP3 ", 
  "PUSH4 0xffffffff ", 
  "REVERT ", 
  "AND ", 
  "PUSH29 0x0100000000000000000000000000000000000000000000000000000000 ", 
  "DUP1 ", 
  "SUB ", 
  "JUMPDEST ", 
  "PUSH1 0x40 ", 
  "JUMPDEST ", 
  "CALLER ", 
  "DUP3 ", 
  "PUSH1 0x40 ", 
  "DUP1 ", 
  "MLOAD ", 
  "DUP1 ", 
  "DUP4 ", 
  "PUSH20 0xffffffffffffffffffffffffffffffffffffffff ", 
  "ADD ", 
  "SWAP2 ", 
  "POP ", 
  "POP ", 
  "PUSH1 0x40 ", 
  "MUL ", 
  "DUP2 ", 
  "MSTORE ", 
  "PUSH1 0x04 ", 
  "SUB ", 
  "ADD ", 
  "DUP1 ", 
  "DUP3 ", 
  "PUSH20 0xffffffffffffffffffffffffffffffffffffffff ", 
  "JUMPDEST ", 
  "JUMP ", 
  "AND ", 
  "PUSH20 0xffffffffffffffffffffffffffffffffffffffff ", 
  "PUSH32 0x56e60a31ff53612407261d12d05ce4b623506086477395bf1a7b299c652ae31a ", 
  "POP ", 
  "AND ", 
  "PUSH20 0xffffffffffffffffffffffffffffffffffffffff ", 
  "AND ", 
  "DUP2 ", 
  "MSTORE ", 
  "PUSH1 0x20 ", 
  "ADD ", 
  "DUP3 ", 
  "DUP2 ", 
  "MSTORE ", 
  "PUSH1 0x20 ", 
  "ADD ", 
  "SWAP3 ", 
  "POP ", 
  "POP ", 
  "AND ", 
  "DUP2 ", 
  "MSTORE ", 
  "PUSH1 0x20 ", 
  "DUP1 ", 
  "ADD ", 
  "SWAP2 ", 
  "POP ", 
  "POP ", 
  "PUSH1 0x20 ", 
  "PUSH1 0x40 ", 
  "REVERT ", 
  "MLOAD ", 
  "DUP1 ", 
  "DUP4 ", 
  "SUB ", 
  "DUP2 ", 
  "PUSH1 0x00 ", 
  "DUP8 ", 
  "DUP1 ", 
  "EXTCODESIZE ", 
  "ISZERO ", 
  "ISZERO ", 
  "PUSH2 0x01c4 ", 
  "SWAP2 ", 
  "JUMPI ", 
  "PUSH1 0x00 ", 
  "DUP1 ", 
  "REVERT ", 
  "JUMPDEST ", 
  "PUSH2 0x02c6 ", 
  "GAS ", 
  "SUB ", 
  "CALL ", 
  "ISZERO ", 
  "ISZERO ", 
  "PUSH2 0x01d5 ", 
  "JUMPI ", 
  "PUSH1 0x00 ", 
  "DUP1 ", 
  "REVERT ", 
  "JUMPDEST ", 
  "POP ", 
  "POP ", 
  "POP ", 
  "PUSH1 0x40 ", 
  "MLOAD ", 
  "DUP1 ", 
  "MLOAD ", 
  "SWAP1 ", 
  "POP ", 
  "DUP2 ", 
  "GT ", 
  "ISZERO ", 
  "ISZERO ", 
  "PUSH2 0x0340 ", 
  "MLOAD ", 
  "JUMPI ", 
  "PUSH1 0x02 ", 
  "MLOAD ", 
  "PUSH1 0x00 ", 
  "SWAP1 ", 
  "SLOAD ", 
  "SWAP1 ", 
  "PUSH2 0x0100 ", 
  "SWAP2 ", 
  "EXP ", 
  "SWAP1 ", 
  "DIV ", 
  "PUSH20 0xffffffffffffffffffffffffffffffffffffffff ", 
  "SUB ", 
  "SWAP1 "
 ], 
 "overflow": false, 
 "money_concurrency": true, 
 "truncation": false
}