{
 "execution_paths": "84", 
 "callstack": false, 
 "reentrancy": false, 
 "modulo": false, 
 "division": false, 
 "execution_time": "53.8381412029", 
 "signedness": false, 
 "evm_code_coverage": "83.7", 
 "underflow": false, 
 "time_dependency": false, 
 "assertion_failure": false, 
 "timeout": false, 
 "dead_code": [
  "JUMPDEST ", 
  "ISZERO ", 
  "PUSH2 0x1182 ", 
  "JUMPI ", 
  "PUSH2 0x1181 ", 
  "DUP4 ", 
  "PUSH1 0x00 ", 
  "DUP2 ", 
  "MLOAD ", 
  "DUP2 ", 
  "LT ", 
  "ISZERO ", 
  "ISZERO ", 
  "PUSH2 0x1078 ", 
  "JUMPI ", 
  "ASSERTFAIL ", 
  "JUMPDEST ", 
  "SWAP1 ", 
  "PUSH1 0x20 ", 
  "ADD ", 
  "SWAP1 ", 
  "PUSH1 0x20 ", 
  "MUL ", 
  "ADD ", 
  "MLOAD ", 
  "DUP4 ", 
  "PUSH1 0x00 ", 
  "DUP2 ", 
  "MLOAD ", 
  "DUP2 ", 
  "LT ", 
  "ISZERO ", 
  "ISZERO ", 
  "PUSH2 0x1091 ", 
  "JUMPI ", 
  "ASSERTFAIL ", 
  "JUMPDEST ", 
  "SWAP1 ", 
  "PUSH1 0x20 ", 
  "ADD ", 
  "SWAP1 ", 
  "PUSH1 0x20 ", 
  "MUL ", 
  "ADD ", 
  "MLOAD ", 
  "DUP6 ", 
  "PUSH1 0x01 ", 
  "DUP2 ", 
  "MLOAD ", 
  "DUP2 ", 
  "LT ", 
  "ISZERO ", 
  "ISZERO ", 
  "PUSH2 0x10aa ", 
  "JUMPI ", 
  "ASSERTFAIL ", 
  "JUMPDEST ", 
  "SWAP1 ", 
  "PUSH1 0x20 ", 
  "ADD ", 
  "SWAP1 ", 
  "PUSH1 0x20 ", 
  "MUL ", 
  "ADD ", 
  "MLOAD ", 
  "DUP6 ", 
  "PUSH1 0x01 ", 
  "DUP2 ", 
  "MLOAD ", 
  "DUP2 ", 
  "LT ", 
  "ISZERO ", 
  "ISZERO ", 
  "PUSH2 0x10c3 ", 
  "JUMPI ", 
  "ASSERTFAIL ", 
  "JUMPDEST ", 
  "SWAP1 ", 
  "PUSH1 0x20 ", 
  "ADD ", 
  "SWAP1 ", 
  "PUSH1 0x20 ", 
  "MUL ", 
  "ADD ", 
  "MLOAD ", 
  "DUP7 ", 
  "PUSH1 0x02 ", 
  "DUP2 ", 
  "MLOAD ", 
  "DUP2 ", 
  "LT ", 
  "ISZERO ", 
  "ISZERO ", 
  "PUSH2 0x10dc ", 
  "JUMPI ", 
  "ASSERTFAIL ", 
  "JUMPDEST ", 
  "SWAP1 ", 
  "PUSH1 0x20 ", 
  "ADD ", 
  "SWAP1 ", 
  "PUSH1 0x20 ", 
  "MUL ", 
  "ADD ", 
  "MLOAD ", 
  "DUP8 ", 
  "PUSH1 0x03 ", 
  "DUP2 ", 
  "MLOAD ", 
  "DUP2 ", 
  "LT ", 
  "ISZERO ", 
  "ISZERO ", 
  "PUSH2 0x10f5 ", 
  "JUMPI ", 
  "ASSERTFAIL ", 
  "JUMPDEST ", 
  "SWAP1 ", 
  "PUSH1 0x20 ", 
  "ADD ", 
  "SWAP1 ", 
  "PUSH1 0x20 ", 
  "MUL ", 
  "ADD ", 
  "MLOAD ", 
  "DUP10 ", 
  "PUSH1 0x02 ", 
  "DUP2 ", 
  "MLOAD ", 
  "DUP2 ", 
  "LT ", 
  "ISZERO ", 
  "ISZERO ", 
  "PUSH2 0x110e ", 
  "JUMPI ", 
  "ASSERTFAIL ", 
  "JUMPDEST ", 
  "SWAP1 ", 
  "PUSH1 0x20 ", 
  "ADD ", 
  "SWAP1 ", 
  "PUSH1 0x20 ", 
  "MUL ", 
  "ADD ", 
  "MLOAD ", 
  "DUP10 ", 
  "PUSH1 0x04 ", 
  "DUP2 ", 
  "MLOAD ", 
  "DUP2 ", 
  "LT ", 
  "ISZERO ", 
  "ISZERO ", 
  "PUSH2 0x1127 ", 
  "JUMPI ", 
  "ASSERTFAIL ", 
  "JUMPDEST ", 
  "SWAP1 ", 
  "PUSH1 0x20 ", 
  "ADD ", 
  "SWAP1 ", 
  "PUSH1 0x20 ", 
  "MUL ", 
  "ADD ", 
  "MLOAD ", 
  "DUP10 ", 
  "PUSH1 0x00 ", 
  "DUP2 ", 
  "MLOAD ", 
  "DUP2 ", 
  "LT ", 
  "ISZERO ", 
  "ISZERO ", 
  "PUSH2 0x1140 ", 
  "JUMPI ", 
  "ASSERTFAIL ", 
  "JUMPDEST ", 
  "SWAP1 ", 
  "PUSH1 0x20 ", 
  "ADD ", 
  "SWAP1 ", 
  "PUSH1 0x20 ", 
  "MUL ", 
  "ADD ", 
  "MLOAD ", 
  "DUP11 ", 
  "PUSH1 0x01 ", 
  "DUP2 ", 
  "MLOAD ", 
  "DUP2 ", 
  "LT ", 
  "ISZERO ", 
  "ISZERO ", 
  "PUSH2 0x1159 ", 
  "JUMPI ", 
  "ASSERTFAIL ", 
  "JUMPDEST ", 
  "SWAP1 ", 
  "PUSH1 0x20 ", 
  "ADD ", 
  "SWAP1 ", 
  "PUSH1 0x20 ", 
  "MUL ", 
  "ADD ", 
  "MLOAD ", 
  "DUP13 ", 
  "PUSH1 0x05 ", 
  "DUP2 ", 
  "MLOAD ", 
  "DUP2 ", 
  "LT ", 
  "ISZERO ", 
  "ISZERO ", 
  "PUSH2 0x1172 ", 
  "JUMPI ", 
  "ASSERTFAIL ", 
  "JUMPDEST ", 
  "SWAP1 ", 
  "PUSH1 0x20 ", 
  "ADD ", 
  "SWAP1 ", 
  "PUSH1 0x20 ", 
  "MUL ", 
  "ADD ", 
  "MLOAD ", 
  "PUSH2 0x0987 ", 
  "JUMP ", 
  "JUMPDEST ", 
  "JUMPDEST ", 
  "POP ", 
  "POP ", 
  "POP ", 
  "JUMP ", 
  "STOP ", 
  "JUMPDEST ", 
  "STOP ", 
  "JUMPDEST ", 
  "STOP ", 
  "JUMPDEST ", 
  "PUSH2 0x0d58 ", 
  "DUP4 ", 
  "PUSH1 0x04 ", 
  "DUP2 ", 
  "MLOAD ", 
  "DUP2 ", 
  "LT ", 
  "ISZERO ", 
  "ISZERO ", 
  "PUSH2 0x0c4f ", 
  "JUMPI ", 
  "ASSERTFAIL ", 
  "JUMPDEST ", 
  "SWAP1 ", 
  "PUSH1 0x20 ", 
  "ADD ", 
  "SWAP1 ", 
  "PUSH1 0x20 ", 
  "MUL ", 
  "ADD ", 
  "MLOAD ", 
  "DUP4 ", 
  "PUSH1 0x06 ", 
  "DUP2 ", 
  "MLOAD ", 
  "DUP2 ", 
  "LT ", 
  "ISZERO ", 
  "ISZERO ", 
  "PUSH2 0x0c68 ", 
  "JUMPI ", 
  "ASSERTFAIL ", 
  "JUMPDEST ", 
  "SWAP1 ", 
  "PUSH1 0x20 ", 
  "ADD ", 
  "SWAP1 ", 
  "PUSH1 0x20 ", 
  "MUL ", 
  "ADD ", 
  "MLOAD ", 
  "DUP6 ", 
  "PUSH1 0x05 ", 
  "DUP2 ", 
  "MLOAD ", 
  "DUP2 ", 
  "LT ", 
  "ISZERO ", 
  "ISZERO ", 
  "PUSH2 0x0c81 ", 
  "JUMPI ", 
  "ASSERTFAIL ", 
  "JUMPDEST ", 
  "SWAP1 ", 
  "PUSH1 0x20 ", 
  "ADD ", 
  "SWAP1 ", 
  "PUSH1 0x20 ", 
  "MUL ", 
  "ADD ", 
  "MLOAD ", 
  "DUP6 ", 
  "PUSH1 0x07 ", 
  "DUP2 ", 
  "MLOAD ", 
  "DUP2 ", 
  "LT ", 
  "ISZERO ", 
  "ISZERO ", 
  "PUSH2 0x0c9a ", 
  "JUMPI ", 
  "ASSERTFAIL ", 
  "JUMPDEST ", 
  "SWAP1 ", 
  "PUSH1 0x20 ", 
  "ADD ", 
  "SWAP1 ", 
  "PUSH1 0x20 ", 
  "MUL ", 
  "ADD ", 
  "MLOAD ", 
  "DUP7 ", 
  "PUSH1 0x08 ", 
  "DUP2 ", 
  "MLOAD ", 
  "DUP2 ", 
  "LT ", 
  "ISZERO ", 
  "ISZERO ", 
  "PUSH2 0x0cb3 ", 
  "JUMPI ", 
  "ASSERTFAIL ", 
  "JUMPDEST ", 
  "SWAP1 ", 
  "PUSH1 0x20 ", 
  "ADD ", 
  "SWAP1 ", 
  "PUSH1 0x20 ", 
  "MUL ", 
  "ADD ", 
  "MLOAD ", 
  "DUP8 ", 
  "PUSH1 0x09 ", 
  "DUP2 ", 
  "MLOAD ", 
  "DUP2 ", 
  "LT ", 
  "ISZERO ", 
  "ISZERO ", 
  "PUSH2 0x0ccc ", 
  "JUMPI ", 
  "ASSERTFAIL ", 
  "JUMPDEST ", 
  "SWAP1 ", 
  "PUSH1 0x20 ", 
  "ADD ", 
  "SWAP1 ", 
  "PUSH1 0x20 ", 
  "MUL ", 
  "ADD ", 
  "MLOAD ", 
  "DUP10 ", 
  "PUSH1 0x06 ", 
  "DUP2 ", 
  "MLOAD ", 
  "DUP2 ", 
  "LT ", 
  "ISZERO ", 
  "ISZERO ", 
  "PUSH2 0x0ce5 ", 
  "JUMPI ", 
  "ASSERTFAIL ", 
  "JUMPDEST ", 
  "SWAP1 ", 
  "PUSH1 0x20 ", 
  "ADD ", 
  "SWAP1 ", 
  "PUSH1 0x20 ", 
  "MUL ", 
  "ADD ", 
  "MLOAD ", 
  "DUP10 ", 
  "PUSH1 0x0a ", 
  "DUP2 ", 
  "MLOAD ", 
  "DUP2 ", 
  "LT ", 
  "ISZERO ", 
  "ISZERO ", 
  "PUSH2 0x0cfe ", 
  "JUMPI ", 
  "ASSERTFAIL ", 
  "JUMPDEST ", 
  "JUMPDEST ", 
  "PUSH1 0x20 ", 
  "ADD ", 
  "SWAP1 ", 
  "PUSH1 0x20 ", 
  "ISZERO ", 
  "MUL ", 
  "ADD ", 
  "MLOAD ", 
  "DUP10 ", 
  "MSTORE ", 
  "PUSH1 0x20 ", 
  "DUP2 ", 
  "ADD ", 
  "DUP2 ", 
  "LT ", 
  "POP ", 
  "ISZERO ", 
  "PUSH2 0x0d17 ", 
  "MLOAD ", 
  "DUP1 ", 
  "SWAP2 ", 
  "SUB ", 
  "SWAP1 ", 
  "RETURN ", 
  "PUSH1 0x20 ", 
  "ADD ", 
  "SWAP1 ", 
  "PUSH1 0x20 ", 
  "MUL ", 
  "ADD ", 
  "MLOAD ", 
  "DUP11 ", 
  "PUSH1 0x03 ", 
  "DUP2 ", 
  "MLOAD ", 
  "DUP2 ", 
  "LT ", 
  "ISZERO ", 
  "ISZERO ", 
  "PUSH2 0x0d30 ", 
  "JUMPI ", 
  "ASSERTFAIL ", 
  "JUMPDEST ", 
  "SWAP1 ", 
  "PUSH1 0x20 ", 
  "ADD ", 
  "SWAP1 ", 
  "PUSH1 0x20 ", 
  "MUL ", 
  "ADD ", 
  "MLOAD ", 
  "DUP13 ", 
  "PUSH1 0x0b ", 
  "DUP2 ", 
  "MLOAD ", 
  "DUP2 ", 
  "LT ", 
  "ISZERO ", 
  "ISZERO ", 
  "PUSH2 0x0d49 ", 
  "JUMPI ", 
  "ASSERTFAIL ", 
  "JUMPDEST ", 
  "SWAP1 ", 
  "PUSH1 0x20 ", 
  "ADD ", 
  "SWAP1 ", 
  "PUSH1 0x20 ", 
  "MUL ", 
  "ADD ", 
  "MLOAD ", 
  "PUSH2 0x0987 ", 
  "JUMP ", 
  "JUMPDEST ", 
  "POP ", 
  "POP ", 
  "POP ", 
  "JUMP ", 
  "JUMPDEST ", 
  "POP ", 
  "JUMPDEST ", 
  "STOP ", 
  "SWAP1 ", 
  "PUSH1 0x40 ", 
  "POP ", 
  "MLOAD ", 
  "DUP1 ", 
  "DUP3 ", 
  "ISZERO ", 
  "POP ", 
  "ISZERO ", 
  "ISZERO ", 
  "DUP2 ", 
  "PUSH1 0x02 ", 
  "JUMP ", 
  "MLOAD ", 
  "SWAP2 ", 
  "POP ", 
  "ISZERO ", 
  "PUSH1 0x40 ", 
  "JUMPI ", 
  "ASSERTFAIL ", 
  "JUMPDEST ", 
  "SWAP1 ", 
  "JUMPDEST ", 
  "SWAP1 ", 
  "POP ", 
  "SWAP4 ", 
  "SWAP3 ", 
  "POP ", 
  "POP ", 
  "POP ", 
  "JUMP "
 ], 
 "overflow": false, 
 "money_concurrency": false, 
 "truncation": false
}